ppackexample/__init__.py
ppackexample/add.py
ppackexample/divide.py
ppackexample/subtract.py
ppackexample/times.py
ppackexample-0.0.1.dist-info/METADATA
ppackexample-0.0.1.dist-info/WHEEL
ppackexample-0.0.1.dist-info/top_level.txt
ppackexample-0.0.1.dist-info/RECORD
