Metadata-Version: 2.1
Name: ppackexample
Version: 0.0.1
Summary: A example Python package
Home-page: https://github.com/shuds13/ppackexample
Author: Bin Yang
Author-email: bin.yang@polymtl.ca
License: BSD 2-clause
Platform: UNKNOWN
Classifier: Development Status :: 1 - Planning
Classifier: Intended Audience :: Science/Research
Classifier: License :: OSI Approved :: BSD License
Classifier: Operating System :: POSIX :: Linux
Classifier: Programming Language :: Python :: 3
Classifier: Programming Language :: Python :: 3.4
Classifier: Programming Language :: Python :: 3.5
Classifier: Programming Language :: Python :: 3.7
Classifier: Programming Language :: Python :: 3.8
Classifier: Programming Language :: Python :: 3.9
Classifier: Programming Language :: Python :: 3.10
Requires-Dist: numpy (>=0.5)
Requires-Dist: scipy
